MANIFEST.in
setup.py
docs/HISTORY.txt
src/dolmen/__init__.py
src/dolmen.menu.egg-info/PKG-INFO
src/dolmen.menu.egg-info/SOURCES.txt
src/dolmen.menu.egg-info/dependency_links.txt
src/dolmen.menu.egg-info/namespace_packages.txt
src/dolmen.menu.egg-info/not-zip-safe
src/dolmen.menu.egg-info/requires.txt
src/dolmen.menu.egg-info/top_level.txt
src/dolmen/menu/README.txt
src/dolmen/menu/__init__.py
src/dolmen/menu/components.py
src/dolmen/menu/configure.zcml
src/dolmen/menu/declarations.py
src/dolmen/menu/interfaces.py
src/dolmen/menu/meta.py
src/dolmen/menu/templates/entry.pt
src/dolmen/menu/templates/menu.pt
src/dolmen/menu/tests/__init__.py
src/dolmen/menu/tests/ftesting.zcml
src/dolmen/menu/tests/test_custom_context.py
src/dolmen/menu/tests/test_decorator.py
src/dolmen/menu/tests/test_directives.py
src/dolmen/menu/tests/test_multidecorators.py